bioscript/__init__.py
bioscript/biovault.py
bioscript/classifier.py
bioscript/cli.py
bioscript/data.py
bioscript/position_aware_matching.py
bioscript/reader.py
bioscript/testing.py
bioscript/types.py
bioscript/utils.py
bioscript/writer.py
bioscript-0.1.5.dist-info/METADATA
bioscript-0.1.5.dist-info/WHEEL
bioscript-0.1.5.dist-info/entry_points.txt
bioscript-0.1.5.dist-info/RECORD
